multirec/__init__.py
multirec/__main__.py
multirec/cli.py
multirec/cli_context.py
multirec/pipeline_registry.py
multirec/settings.py
multirec/extras/__init__.py
multirec/extras/datasets/__init__.py
multirec/extras/datasets/mongo_dataset.py
multirec/pipelines/__init__.py
multirec/pipelines/build_recommendations_based_similar/__init__.py
multirec/pipelines/build_recommendations_based_similar/nodes.py
multirec/pipelines/build_recommendations_based_similar/pipeline.py
multirec/pipelines/drop_nan_column/__init__.py
multirec/pipelines/drop_nan_column/nodes.py
multirec/pipelines/drop_nan_column/pipeline.py
multirec/templates/conf/base/catalog.yml
multirec/templates/conf/base/logging.yml
multirec/templates/conf/base/parameters.yml
multirec/templates/conf/base/parameters/build_recommendations_based_similar.yml
multirec/templates/conf/local/.gitkeep
multirec/templates/conf/local/credentials.yml
multirec/templates/data/01_raw/.gitkeep
multirec/templates/data/02_intermediate/.gitkeep
multirec/templates/data/03_primary/.gitkeep
multirec/templates/data/04_feature/.gitkeep
multirec/templates/data/05_model_input/.gitkeep
multirec/templates/data/06_models/.gitkeep
multirec/templates/data/07_model_output/.gitkeep
multirec/templates/data/08_reporting/.gitkeep
multirec/templates/logs/.gitkeep
multirec/web/__init__.py
multirec/web/app.py
multirec/web/constants.py
multirec/web/exceptions.py
multirec/web/main_page.py
multirec/web/utils.py
multirec-0.2.dist-info/METADATA
multirec-0.2.dist-info/WHEEL
multirec-0.2.dist-info/entry_points.txt
multirec-0.2.dist-info/top_level.txt
multirec-0.2.dist-info/RECORD
