Metadata-Version: 2.1
Name: multirec
Version: 0.2
Author: CapBlood
Project-URL: Homepage, https://github.com/CapBlood/multi-recommender.git
Project-URL: documentation, https://capblood.github.io/multi-recommender/
Requires-Dist: black (~=22.0)
Requires-Dist: flake8 (<5.0,>=3.7.9)
Requires-Dist: ipython (<8.0,>=7.31.1)
Requires-Dist: isort (~=5.0)
Requires-Dist: jupyter (~=1.0)
Requires-Dist: jupyterlab-server (<2.16.0,>=2.11.1)
Requires-Dist: jupyterlab (~=3.0)
Requires-Dist: kedro (~=0.18.4)
Requires-Dist: kedro-viz
Requires-Dist: kedro-telemetry (~=0.2.0)
Requires-Dist: nbstripout (~=0.4)
Requires-Dist: pytest-cov (~=3.0)
Requires-Dist: pytest-mock (<2.0,>=1.7.1)
Requires-Dist: pytest (~=6.2)
Requires-Dist: pandas (==1.4.2)
Requires-Dist: scikit-learn (==1.0.2)
Requires-Dist: streamlit
Provides-Extra: docs
Requires-Dist: docutils (<0.18.0) ; extra == 'docs'
Requires-Dist: nbstripout (~=0.4) ; extra == 'docs'
Requires-Dist: ipykernel (<7.0,>=5.3) ; extra == 'docs'
Requires-Dist: Jinja2 (<3.1.0) ; extra == 'docs'
Requires-Dist: myst-parser (~=0.17.2) ; extra == 'docs'
